meinsweeper/__init__.py
meinsweeper/due.py
meinsweeper/logo.png
meinsweeper/meinsweeper.py
meinsweeper/version.py
meinsweeper/modules/__init__.py
meinsweeper/modules/check_gpu.py
meinsweeper/modules/configuration.py
meinsweeper/modules/logger.py
meinsweeper/modules/run_manager.py
meinsweeper/modules/task.py
meinsweeper/modules/helpers/debug_logging.py
meinsweeper/modules/helpers/retry.py
meinsweeper/modules/helpers/utils.py
meinsweeper/modules/nodes/__init__.py
meinsweeper/modules/nodes/abstract.py
meinsweeper/modules/nodes/local_async_node.py
meinsweeper/modules/nodes/ssh_node.py
meinsweeper/tests/icl_run_test.py
meinsweeper/tests/logger_test.py
meinsweeper/tests/test_local_async_node.py
meinsweeper/tests/test_run_manager.py
meinsweeper/tests/test_run_sweep.py
meinsweeper/tests/test_run_sweep_with_gpu_occupation.py
meinsweeper/tests/test_simple_mslogger.py
meinsweeper-0.3.8.dist-info/LICENSE
meinsweeper-0.3.8.dist-info/METADATA
meinsweeper-0.3.8.dist-info/WHEEL
meinsweeper-0.3.8.dist-info/top_level.txt
meinsweeper-0.3.8.dist-info/RECORD
