Metadata-Version: 2.1
Name: meinsweeper
Version: 0.3.8
Summary: MeinSweeper is a light-weight framework for running experiments on arbitrary compute nodes
Author-email: Alex Spies <alex@afspies.com>
License: The MIT License (MIT)
Project-URL: Homepage, https://github.com/afspies/meinsweeper
Project-URL: Bug Tracker, https://github.com/afspies/meinsweeper/issues
Project-URL: Icon, https://raw.githubusercontent.com/afspies/meinsweeper/master/meinsweeper/logo.png
Classifier: Programming Language :: Python :: 3
Classifier: License :: OSI Approved :: MIT License
Classifier: Operating System :: OS Independent
Requires-Python: >=3.7
License-File: LICENSE
Requires-Dist: asyncssh
Requires-Dist: rich
Requires-Dist: psutil
Requires-Dist: duecredit
